aks_pip/__init__.py
aks_pip/cal.py
aks_pip/version.py
aks_pip-0.0.1.dist-info/licenses/LICENCE
aks_pip-0.0.1.dist-info/METADATA
aks_pip-0.0.1.dist-info/WHEEL
aks_pip-0.0.1.dist-info/top_level.txt
aks_pip-0.0.1.dist-info/RECORD
