Metadata-Version: 2.4
Name: aks_pip
Version: 0.0.1
Summary: this xyz  package
Author-email: Rahul Kumar <rahul8969051051@gmail.com>
License-Expression: MIT
Project-URL: Homepage, https://github.com/pypa/sampleproject
Project-URL: Issues, https://github.com/pypa/sampleproject/issues
Keywords: sample,setuptools,development
Classifier: Programming Language :: Python :: 3
Classifier: Operating System :: OS Independent
Requires-Python: >=3.2
License-File: LICENCE
Dynamic: license-file
